sqlalchemy_sqlite_session/__init__.py
sqlalchemy_sqlite_session/adapters.py
sqlalchemy_sqlite_session-0.2.0.dist-info/LICENSE
sqlalchemy_sqlite_session-0.2.0.dist-info/METADATA
sqlalchemy_sqlite_session-0.2.0.dist-info/WHEEL
sqlalchemy_sqlite_session-0.2.0.dist-info/top_level.txt
sqlalchemy_sqlite_session-0.2.0.dist-info/RECORD
